segment_downloader/__init__.py
segment_downloader/authenticate.py
segment_downloader/cli.py
segment_downloader/constants.py
segment_downloader/downloader.py
segment_downloader/exceptions.py
segment_downloader-0.1.3.dist-info/WHEEL
segment_downloader-0.1.3.dist-info/entry_points.txt
segment_downloader-0.1.3.dist-info/METADATA
segment_downloader-0.1.3.dist-info/RECORD
