Metadata-Version: 2.3
Name: segment_downloader
Version: 0.1.3
Summary: Allows to fully download a Strava leaderboard and saves it into a CSV file for further statistical analysis
Requires-Dist: selenium~=4.25.0
Requires-Python: >=3.10
